{
  "args": {
    "bo_profile": "fast_candidates",
    "input": "C:\\PyCharm\\Blueness\\logs\\May_10_full_log\\data_corrected.xlsx",
    "sheet": "Corrected Data",
    "target": "intensity",
    "hrp": 0.0001,
    "hrp_atol": 1e-12,
    "filter_ctrl": true,
    "device": "cpu",
    "seed": 42,
    "output_dir": "C:\\PyCharm\\Blueness\\logs\\May_11_full_log\\fast_candidates",
    "models": [
      "new_additive_set"
    ],
    "k_max": 4,
    "fit_maxiter": 100,
    "training_fit_diagnostics": false,
    "matrix_diagnostics": false,
    "loo_diagnostics": false,
    "kernel_parameter_summary": false,
    "acq_stability_diagnostics": false,
    "stability_mc_samples": 64,
    "stability_repeats": 5,
    "acq_pool_size": 512,
    "skip_candidates": false,
    "q": 32,
    "num_top_subspaces": 20,
    "sobol_max_samples": 128,
    "screen_mc_samples": 16,
    "num_restarts": 5,
    "raw_samples": 128,
    "acq_maxiter": 50,
    "refine_mc_samples": 32,
    "eval_batch_size": 256
  },
  "data": {
    "rows_after_filters": 461,
    "target_mean": 85428.2827853377,
    "target_std": 26014.563565290526,
    "target_min": -52.12563452,
    "target_max": 151518.1277267,
    "active_count_dist": {
      "1": 198,
      "2": 231,
      "0": 32
    },
    "rows_any_additive_gt_encoding_hi": 0,
    "additive_gt_encoding_hi_counts": {},
    "raw_rows": 461,
    "unique_encoded_rows": 446,
    "duplicates_merged": 15,
    "encoded_dim": 46,
    "n_additives": 22
  },
  "models": {
    "new_additive_set": {
      "fit_seconds": 11.26714301109314,
      "mll": -0.2183955284834062,
      "n_subspaces_total": 9109,
      "n_subspaces_top": 20,
      "screen_best": 10.189162685232262,
      "screen_worst_top": 9.541045307201944,
      "screen_active_count_dist": {
        "4": 19,
        "3": 1
      },
      "screen_sample_stats_by_n_free": {
        "2": 4,
        "3": 176,
        "4": 3696,
        "5": 49280,
        "6": 468160
      },
      "candidate_opt_seconds": 1224.7396953105927,
      "candidate_joint_acq": 10.996296363396139,
      "candidate_unique_before_topq": 32,
      "candidate_n": 32,
      "candidate_active_count_dist": {
        "4": 32
      },
      "candidate_additive_counts": {
        "imidazole": 32,
        "cacl2": 32,
        "cmc": 19,
        "bsa": 18,
        "sucrose": 10,
        "edta": 7,
        "feso4": 5,
        "peg20k": 4,
        "peg200k": 1
      },
      "candidate_pair_counts": {
        "imidazole+cacl2": 32,
        "cmc+imidazole": 19,
        "cmc+cacl2": 19,
        "bsa+imidazole": 18,
        "bsa+cacl2": 18,
        "imidazole+sucrose": 10,
        "sucrose+cacl2": 10,
        "imidazole+edta": 7,
        "edta+cacl2": 7,
        "cmc+bsa": 6,
        "bsa+sucrose": 6,
        "imidazole+feso4": 5,
        "cacl2+feso4": 5,
        "cmc+sucrose": 4,
        "peg20k+imidazole": 4,
        "peg20k+cacl2": 4,
        "bsa+edta": 3,
        "cmc+feso4": 3,
        "cmc+edta": 3,
        "cmc+peg20k": 3
      },
      "candidate_acq_mean": 10.52092075739907,
      "candidate_acq_min": 9.955050557425642,
      "candidate_acq_max": 10.875304299900566
    }
  }
}